[
  {
    "__type__": "cc.SpriteFrame",
    "content": {
      "name": "double-arrow-bottom",
      "texture": "1ba2d2e85",
      "rect": [
        115,
        2,
        195,
        178
      ],
      "offset": [
        1.5,
        0
      ],
      "originalSize": [
        200,
        200
      ]
    }
  },
  [
    {
      "__type__": "cc.SceneAsset",
      "_name": "PropsMode",
      "scene": {
        "__id__": 1
      },
      "asyncLoadAssets": null
    },
    {
      "__type__": "cc.Scene",
      "_name": "New Node",
      "_children": [
        {
          "__id__": 2
        }
      ],
      "_anchorPoint": {
        "__type__": "cc.Vec2"
      },
      "autoReleaseAssets": false
    },
    {
      "__type__": "cc.Node",
      "_name": "Canvas",
      "_parent": {
        "__id__": 1
      },
      "_children": [
        {
          "__id__": 3
        }
      ],
      "_components": [
        {
          "__type__": "cc.Canvas",
          "node": {
            "__id__": 2
          },
          "_designResolution": {
            "__type__": "cc.Size",
            "width": 960,
            "height": 540
          },
          "_fitWidth": true,
          "_fitHeight": false
        },
        {
          "__type__": "b605bpAEohD4KevRc8lgwUh",
          "node": {
            "__id__": 2
          }
        },
        null
      ],
      "_id": "eekFZkkIpHOpHJ2YvEOtSt",
      "_contentSize": {
        "__type__": "cc.Size",
        "width": 960,
        "height": 540
      },
      "_position": {
        "__type__": "cc.Vec2",
        "x": 480,
        "y": 270
      }
    },
    {
      "__type__": "cc.Node",
      "_name": "map",
      "_parent": {
        "__id__": 2
      },
      "_children": [
        {
          "__id__": 4
        },
        {
          "__id__": 7
        }
      ],
      "_components": [
        {
          "__type__": "616b0xKWLtFY5rUTgK/fQ7K",
          "node": {
            "__id__": 3
          },
          "map": {
            "__id__": 3
          },
          "planet": {
            "__uuid__": "79oFtgrk5Lr6u9PUVn//oQ"
          }
        }
      ],
      "_contentSize": {
        "__type__": "cc.Size",
        "width": 8000,
        "height": 8000
      }
    },
    {
      "__type__": "cc.Node",
      "_name": "bg",
      "_parent": {
        "__id__": 3
      },
      "_children": [
        {
          "__id__": 5
        },
        {
          "__id__": 6
        }
      ],
      "_components": [
        {
          "__type__": "cc.Mask",
          "node": {
            "__id__": 4
          },
          "_enabled": false,
          "_type": 1,
          "_segements": 128
        },
        {
          "__type__": "cc.RigidBody",
          "node": {
            "__id__": 4
          },
          "_type": 0,
          "enabledContactListener": true
        },
        {
          "__type__": "cc.PhysicsBoxCollider",
          "node": {
            "__id__": 4
          },
          "tag": 100,
          "_density": 100,
          "_friction": 0.5,
          "_offset": {
            "__type__": "cc.Vec2",
            "x": -4000
          },
          "_size": {
            "__type__": "cc.Size",
            "width": 10,
            "height": 8000
          }
        },
        {
          "__type__": "cc.PhysicsBoxCollider",
          "node": {
            "__id__": 4
          },
          "tag": 100,
          "_density": 100,
          "_friction": 0.5,
          "_offset": {
            "__type__": "cc.Vec2",
            "x": 4000
          },
          "_size": {
            "__type__": "cc.Size",
            "width": 10,
            "height": 8000
          }
        },
        {
          "__type__": "cc.PhysicsBoxCollider",
          "node": {
            "__id__": 4
          },
          "tag": 100,
          "_density": 100,
          "_friction": 0.5,
          "_offset": {
            "__type__": "cc.Vec2",
            "y": 4000
          },
          "_size": {
            "__type__": "cc.Size",
            "width": 8000,
            "height": 10
          }
        },
        {
          "__type__": "cc.PhysicsBoxCollider",
          "node": {
            "__id__": 4
          },
          "tag": 100,
          "_density": 100,
          "_friction": 0.5,
          "_offset": {
            "__type__": "cc.Vec2",
            "y": -4000
          },
          "_size": {
            "__type__": "cc.Size",
            "width": 8000,
            "height": 10
          }
        }
      ],
      "_contentSize": {
        "__type__": "cc.Size",
        "width": 8000,
        "height": 8000
      },
      "groupIndex": 4
    },
    {
      "__type__": "cc.Node",
      "_name": "paper",
      "_parent": {
        "__id__": 4
      },
      "_components": [
        {
          "__type__": "cc.Sprite",
          "node": {
            "__id__": 5
          },
          "_spriteFrame": {
            "__uuid__": "a2MjXRFdtLlYQ5ouAFv/+R"
          },
          "_sizeMode": 0
        }
      ],
      "_contentSize": {
        "__type__": "cc.Size",
        "width": 8000,
        "height": 8000
      }
    },
    {
      "__type__": "cc.Node",
      "_name": "+",
      "_parent": {
        "__id__": 4
      },
      "_components": [
        {
          "__type__": "cc.Sprite",
          "node": {
            "__id__": 6
          },
          "_spriteFrame": {
            "__uuid__": "9aacc1cp9PfrHiiQDkP4z7"
          },
          "_type": 2,
          "_sizeMode": 0
        }
      ],
      "_opacity": 30,
      "_contentSize": {
        "__type__": "cc.Size",
        "width": 8000,
        "height": 8000
      }
    },
    {
      "__type__": "cc.Node",
      "_name": "ObjectGroup",
      "_parent": {
        "__id__": 3
      },
      "_children": [
        {
          "__id__": 8
        }
      ]
    },
    {
      "__type__": "cc.Node",
      "_name": "PropsGroup",
      "_parent": {
        "__id__": 7
      },
      "_children": [
        {
          "__id__": 9
        },
        {
          "__id__": 12
        },
        {
          "__id__": 15
        },
        {
          "__id__": 18
        }
      ],
      "_components": [
        {
          "__type__": "cc.Layout",
          "node": {
            "__id__": 8
          },
          "_layoutSize": {
            "__type__": "cc.Size",
            "width": 300,
            "height": 40
          },
          "_resize": 1,
          "_N$layoutType": 3,
          "_N$spacingX": 30,
          "_N$spacingY": 30
        }
      ],
      "_contentSize": {
        "__type__": "cc.Size",
        "width": 300,
        "height": 40
      }
    },
    {
      "__type__": "cc.Node",
      "_name": "star",
      "_parent": {
        "__id__": 8
      },
      "_children": [
        {
          "__id__": 10
        },
        {
          "__id__": 11
        }
      ],
      "_components": [
        {
          "__type__": "cc.CircleCollider",
          "node": {
            "__id__": 9
          },
          "_radius": 20
        }
      ],
      "_contentSize": {
        "__type__": "cc.Size",
        "width": 40,
        "height": 40
      },
      "_position": {
        "__type__": "cc.Vec2",
        "x": -130
      }
    },
    {
      "__type__": "cc.Node",
      "_name": "bg",
      "_parent": {
        "__id__": 9
      },
      "_components": [
        {
          "__type__": "cc.Sprite",
          "node": {
            "__id__": 10
          },
          "_spriteFrame": {
            "__uuid__": "55lWtldR1Geph6loTvYsec"
          },
          "_sizeMode": 0
        }
      ],
      "_contentSize": {
        "__type__": "cc.Size",
        "width": 40,
        "height": 40
      }
    },
    {
      "__type__": "cc.Node",
      "_name": "icon",
      "_parent": {
        "__id__": 9
      },
      "_components": [
        {
          "__type__": "cc.Sprite",
          "node": {
            "__id__": 11
          },
          "_spriteFrame": {
            "__uuid__": "f4217NZahDaLGC9FMudZgy"
          },
          "_sizeMode": 0,
          "_isTrimmedMode": false
        }
      ],
      "_color": {
        "__type__": "cc.Color"
      },
      "_contentSize": {
        "__type__": "cc.Size",
        "width": 30,
        "height": 30
      }
    },
    {
      "__type__": "cc.Node",
      "_name": "double",
      "_parent": {
        "__id__": 8
      },
      "_children": [
        {
          "__id__": 13
        },
        {
          "__id__": 14
        }
      ],
      "_components": [
        {
          "__type__": "cc.CircleCollider",
          "node": {
            "__id__": 12
          },
          "_radius": 20
        }
      ],
      "_contentSize": {
        "__type__": "cc.Size",
        "width": 40,
        "height": 40
      },
      "_position": {
        "__type__": "cc.Vec2",
        "x": -60
      }
    },
    {
      "__type__": "cc.Node",
      "_name": "bg",
      "_parent": {
        "__id__": 12
      },
      "_components": [
        {
          "__type__": "cc.Sprite",
          "node": {
            "__id__": 13
          },
          "_spriteFrame": {
            "__uuid__": "55lWtldR1Geph6loTvYsec"
          },
          "_sizeMode": 0
        }
      ],
      "_contentSize": {
        "__type__": "cc.Size",
        "width": 40,
        "height": 40
      }
    },
    {
      "__type__": "cc.Node",
      "_name": "icon",
      "_parent": {
        "__id__": 12
      },
      "_components": [
        {
          "__type__": "cc.Sprite",
          "node": {
            "__id__": 14
          },
          "_spriteFrame": {
            "__uuid__": "86YOfiwExJ0rIABK6IBuoW"
          },
          "_sizeMode": 0,
          "_isTrimmedMode": false
        }
      ],
      "_color": {
        "__type__": "cc.Color"
      },
      "_contentSize": {
        "__type__": "cc.Size",
        "width": 30,
        "height": 30
      }
    },
    {
      "__type__": "cc.Node",
      "_name": "fast",
      "_parent": {
        "__id__": 8
      },
      "_children": [
        {
          "__id__": 16
        },
        {
          "__id__": 17
        }
      ],
      "_components": [
        {
          "__type__": "cc.CircleCollider",
          "node": {
            "__id__": 15
          },
          "_radius": 20
        }
      ],
      "_contentSize": {
        "__type__": "cc.Size",
        "width": 40,
        "height": 40
      },
      "_position": {
        "__type__": "cc.Vec2",
        "x": 10
      }
    },
    {
      "__type__": "cc.Node",
      "_name": "bg",
      "_parent": {
        "__id__": 15
      },
      "_components": [
        {
          "__type__": "cc.Sprite",
          "node": {
            "__id__": 16
          },
          "_spriteFrame": {
            "__uuid__": "55lWtldR1Geph6loTvYsec"
          },
          "_sizeMode": 0
        }
      ],
      "_contentSize": {
        "__type__": "cc.Size",
        "width": 40,
        "height": 40
      }
    },
    {
      "__type__": "cc.Node",
      "_name": "icon",
      "_parent": {
        "__id__": 15
      },
      "_components": [
        {
          "__type__": "cc.Sprite",
          "node": {
            "__id__": 17
          },
          "_spriteFrame": {
            "__uuid__": "5eDBsAOG1G0JK3UFWs+fjJ"
          },
          "_sizeMode": 0,
          "_isTrimmedMode": false
        }
      ],
      "_color": {
        "__type__": "cc.Color"
      },
      "_contentSize": {
        "__type__": "cc.Size",
        "width": 25,
        "height": 25
      },
      "_position": {
        "__type__": "cc.Vec2",
        "y": 2
      }
    },
    {
      "__type__": "cc.Node",
      "_name": "slow",
      "_parent": {
        "__id__": 8
      },
      "_children": [
        {
          "__id__": 19
        },
        {
          "__id__": 20
        }
      ],
      "_components": [
        {
          "__type__": "cc.CircleCollider",
          "node": {
            "__id__": 18
          },
          "_radius": 20
        }
      ],
      "_contentSize": {
        "__type__": "cc.Size",
        "width": 40,
        "height": 40
      },
      "_position": {
        "__type__": "cc.Vec2",
        "x": 80
      }
    },
    {
      "__type__": "cc.Node",
      "_name": "bg",
      "_parent": {
        "__id__": 18
      },
      "_components": [
        {
          "__type__": "cc.Sprite",
          "node": {
            "__id__": 19
          },
          "_spriteFrame": {
            "__uuid__": "55lWtldR1Geph6loTvYsec"
          },
          "_sizeMode": 0
        }
      ],
      "_contentSize": {
        "__type__": "cc.Size",
        "width": 40,
        "height": 40
      }
    },
    {
      "__type__": "cc.Node",
      "_name": "icon",
      "_parent": {
        "__id__": 18
      },
      "_components": [
        {
          "__type__": "cc.Sprite",
          "node": {
            "__id__": 20
          },
          "_spriteFrame": {
            "__uuid__": "13peA/duZAxLZI4wqgldIt"
          },
          "_sizeMode": 0,
          "_isTrimmedMode": false
        }
      ],
      "_color": {
        "__type__": "cc.Color"
      },
      "_contentSize": {
        "__type__": "cc.Size",
        "width": 25,
        "height": 25
      },
      "_position": {
        "__type__": "cc.Vec2",
        "y": -2
      }
    }
  ],
  {
    "__type__": "cc.SpriteFrame",
    "content": {
      "name": "circle",
      "texture": "8cdeBnt0tAEpfKUW9ujATq",
      "rect": [
        3,
        3,
        194,
        194
      ],
      "offset": [
        0,
        0
      ],
      "originalSize": [
        200,
        200
      ]
    }
  },
  {
    "__type__": "cc.SpriteFrame",
    "content": {
      "name": "double-arrow-top",
      "texture": "1ba2d2e85",
      "rect": [
        2,
        603,
        195,
        178
      ],
      "offset": [
        1.5,
        0
      ],
      "originalSize": [
        200,
        200
      ]
    }
  },
  {
    "__type__": "cc.SpriteFrame",
    "content": {
      "name": "two",
      "texture": "1ba2d2e85",
      "rect": [
        182,
        785,
        76,
        176
      ],
      "offset": [
        0,
        0
      ],
      "originalSize": [
        200,
        200
      ]
    }
  },
  {
    "__type__": "cc.SpriteFrame",
    "content": {
      "name": "grid",
      "texture": "aemh6QOV1GIIZye8orXwas",
      "rect": [
        0,
        0,
        128,
        128
      ],
      "offset": [
        0,
        0
      ],
      "originalSize": [
        128,
        128
      ]
    }
  },
  {
    "__type__": "cc.SpriteFrame",
    "content": {
      "name": "default_sprite_splash",
      "texture": "02delMVqdBD70a/HSD99FK",
      "rect": [
        0,
        0,
        2,
        2
      ],
      "offset": [
        0,
        0
      ],
      "originalSize": [
        2,
        2
      ]
    }
  },
  {
    "__type__": "cc.SpriteFrame",
    "content": {
      "name": "planet",
      "texture": "1ba2d2e85",
      "rect": [
        314,
        2,
        200,
        126
      ],
      "offset": [
        0,
        0
      ],
      "originalSize": [
        200,
        200
      ]
    }
  }
]