[
  {
    "__type__": "cc.SpriteFrame",
    "content": {
      "name": "weibo",
      "texture": "1d139866a",
      "rect": [
        209,
        413,
        196,
        196
      ],
      "offset": [
        0,
        0
      ],
      "originalSize": [
        200,
        200
      ]
    }
  },
  {
    "__type__": "cc.SpriteFrame",
    "content": {
      "name": "GitHub",
      "texture": "1d139866a",
      "rect": [
        3,
        3,
        205,
        200
      ],
      "offset": [
        0,
        0
      ],
      "originalSize": [
        205,
        200
      ]
    }
  },
  [
    {
      "__type__": "cc.SceneAsset",
      "_name": "About",
      "scene": {
        "__id__": 1
      },
      "asyncLoadAssets": null
    },
    {
      "__type__": "cc.Scene",
      "_name": "New Node",
      "_children": [
        {
          "__id__": 2
        }
      ],
      "_anchorPoint": {
        "__type__": "cc.Vec2"
      },
      "autoReleaseAssets": false
    },
    {
      "__type__": "cc.Node",
      "_name": "Canvas",
      "_parent": {
        "__id__": 1
      },
      "_children": [
        {
          "__id__": 3
        },
        {
          "__id__": 12
        }
      ],
      "_components": [
        {
          "__type__": "cc.Canvas",
          "node": {
            "__id__": 2
          },
          "_designResolution": {
            "__type__": "cc.Size",
            "width": 960,
            "height": 540
          }
        }
      ],
      "_id": "3amSCQM4RHW616sStdlyVC",
      "_contentSize": {
        "__type__": "cc.Size",
        "width": 960,
        "height": 540
      },
      "_position": {
        "__type__": "cc.Vec2",
        "x": 480,
        "y": 270
      }
    },
    {
      "__type__": "cc.Node",
      "_name": "About",
      "_parent": {
        "__id__": 2
      },
      "_children": [
        {
          "__id__": 4
        },
        {
          "__id__": 5
        },
        {
          "__id__": 6
        },
        {
          "__id__": 7
        }
      ],
      "_components": [
        {
          "__type__": "cc.Layout",
          "node": {
            "__id__": 3
          },
          "_layoutSize": {
            "__type__": "cc.Size",
            "width": 960,
            "height": 580
          },
          "_resize": 1,
          "_N$layoutType": 2,
          "_N$paddingTop": 100,
          "_N$paddingBottom": 100,
          "_N$spacingY": 50
        },
        {
          "__type__": "cc.Widget",
          "node": {
            "__id__": 3
          },
          "_target": {
            "__id__": 2
          },
          "_alignFlags": 45,
          "_top": -20,
          "_bottom": -20,
          "_originalWidth": 200,
          "_originalHeight": 150
        },
        {
          "__type__": "396a4yO9/tOUaxE1hWIsU2E",
          "node": {
            "__id__": 3
          }
        }
      ],
      "_contentSize": {
        "__type__": "cc.Size",
        "width": 960,
        "height": 580
      }
    },
    {
      "__type__": "cc.Node",
      "_name": "Logo",
      "_parent": {
        "__id__": 3
      },
      "_components": [
        {
          "__type__": "cc.Sprite",
          "node": {
            "__id__": 4
          },
          "_spriteFrame": {
            "__uuid__": "8folOeXkpHP6/jaM4zVsTM"
          },
          "_sizeMode": 0
        },
        {
          "__type__": "cc.Animation",
          "node": {
            "__id__": 4
          },
          "_defaultClip": {
            "__uuid__": "33csriJcVDQJHVPIA6YPqP"
          },
          "_clips": [
            {
              "__uuid__": "33csriJcVDQJHVPIA6YPqP"
            }
          ],
          "playOnLoad": true
        },
        {
          "__type__": "cc.Button",
          "node": {
            "__id__": 4
          },
          "transition": 3,
          "_N$target": {
            "__id__": 4
          }
        }
      ],
      "_contentSize": {
        "__type__": "cc.Size",
        "width": 100,
        "height": 100
      },
      "_position": {
        "__type__": "cc.Vec2",
        "y": 140
      }
    },
    {
      "__type__": "cc.Node",
      "_name": "PaperStar",
      "_parent": {
        "__id__": 3
      },
      "_components": [
        {
          "__type__": "cc.Label",
          "node": {
            "__id__": 5
          },
          "_useOriginalSize": false,
          "_N$string": "Hello, Paper Star!",
          "_N$horizontalAlign": 1,
          "_N$verticalAlign": 1,
          "_N$fontFamily": "Lato, \"PingFang SC\", \"Microsoft YaHei\", Arial, sans-serif"
        },
        {
          "__type__": "cc.Button",
          "node": {
            "__id__": 5
          },
          "transition": 3,
          "clickEvents": [
            {
              "__type__": "cc.ClickEvent",
              "target": {
                "__id__": 3
              },
              "component": "About",
              "handler": "openProjectShow"
            }
          ],
          "_N$target": {
            "__id__": 5
          }
        }
      ],
      "_contentSize": {
        "__type__": "cc.Size",
        "width": 304,
        "height": 40
      },
      "_position": {
        "__type__": "cc.Vec2",
        "y": 20
      }
    },
    {
      "__type__": "cc.Node",
      "_name": "@YunYouJun",
      "_parent": {
        "__id__": 3
      },
      "_components": [
        {
          "__type__": "cc.Label",
          "node": {
            "__id__": 6
          },
          "_useOriginalSize": false,
          "_N$string": "@YunYouJun",
          "_N$horizontalAlign": 1,
          "_N$verticalAlign": 1,
          "_N$fontFamily": "Lato, \"PingFang SC\", \"Microsoft YaHei\", Arial, sans-serif"
        },
        {
          "__type__": "cc.Button",
          "node": {
            "__id__": 6
          },
          "transition": 3,
          "clickEvents": [
            {
              "__type__": "cc.ClickEvent",
              "target": {
                "__id__": 3
              },
              "component": "About",
              "handler": "openAuthorGitHub"
            }
          ],
          "_N$target": {
            "__id__": 6
          }
        }
      ],
      "_contentSize": {
        "__type__": "cc.Size",
        "width": 221,
        "height": 40
      },
      "_position": {
        "__type__": "cc.Vec2",
        "y": -70
      }
    },
    {
      "__type__": "cc.Node",
      "_name": "Icons",
      "_parent": {
        "__id__": 3
      },
      "_children": [
        {
          "__id__": 8
        },
        {
          "__id__": 9
        },
        {
          "__id__": 10
        },
        {
          "__id__": 11
        }
      ],
      "_components": [
        {
          "__type__": "cc.Layout",
          "node": {
            "__id__": 7
          },
          "_layoutSize": {
            "__type__": "cc.Size",
            "width": 260,
            "height": 50
          },
          "_resize": 1,
          "_N$layoutType": 1,
          "_N$spacingX": 20
        }
      ],
      "_contentSize": {
        "__type__": "cc.Size",
        "width": 260,
        "height": 50
      },
      "_position": {
        "__type__": "cc.Vec2",
        "y": -165
      }
    },
    {
      "__type__": "cc.Node",
      "_name": "GitHub",
      "_parent": {
        "__id__": 7
      },
      "_components": [
        {
          "__type__": "cc.Sprite",
          "node": {
            "__id__": 8
          },
          "_spriteFrame": {
            "__uuid__": "0fk3EHHvFNFprD3Qdb0t+2"
          },
          "_sizeMode": 0
        },
        {
          "__type__": "cc.Button",
          "node": {
            "__id__": 8
          },
          "transition": 3,
          "clickEvents": [
            {
              "__type__": "cc.ClickEvent",
              "target": {
                "__id__": 3
              },
              "component": "About",
              "handler": "openProjectGitHub"
            }
          ],
          "_N$target": {
            "__id__": 8
          }
        }
      ],
      "_contentSize": {
        "__type__": "cc.Size",
        "width": 50,
        "height": 50
      },
      "_position": {
        "__type__": "cc.Vec2",
        "x": -105
      }
    },
    {
      "__type__": "cc.Node",
      "_name": "Weibo",
      "_parent": {
        "__id__": 7
      },
      "_components": [
        {
          "__type__": "cc.Sprite",
          "node": {
            "__id__": 9
          },
          "_spriteFrame": {
            "__uuid__": "0bFSA9mq1LOa31avhkfzQs"
          },
          "_sizeMode": 0
        },
        {
          "__type__": "cc.Button",
          "node": {
            "__id__": 9
          },
          "transition": 3,
          "clickEvents": [
            {
              "__type__": "cc.ClickEvent",
              "target": {
                "__id__": 3
              },
              "component": "About",
              "handler": "openAuthorWeibo"
            }
          ],
          "_N$target": {
            "__id__": 9
          }
        }
      ],
      "_contentSize": {
        "__type__": "cc.Size",
        "width": 50,
        "height": 50
      },
      "_position": {
        "__type__": "cc.Vec2",
        "x": -35
      }
    },
    {
      "__type__": "cc.Node",
      "_name": "Web",
      "_parent": {
        "__id__": 7
      },
      "_components": [
        {
          "__type__": "cc.Sprite",
          "node": {
            "__id__": 10
          },
          "_spriteFrame": {
            "__uuid__": "990EufTUdCRbqeFPKcdFL4"
          },
          "_sizeMode": 0
        },
        {
          "__type__": "cc.Button",
          "node": {
            "__id__": 10
          },
          "transition": 3,
          "clickEvents": [
            {
              "__type__": "cc.ClickEvent",
              "target": {
                "__id__": 3
              },
              "component": "About",
              "handler": "openGameWeb"
            }
          ],
          "_N$target": {
            "__id__": 10
          }
        }
      ],
      "_contentSize": {
        "__type__": "cc.Size",
        "width": 50,
        "height": 50
      },
      "_position": {
        "__type__": "cc.Vec2",
        "x": 35
      }
    },
    {
      "__type__": "cc.Node",
      "_name": "Email",
      "_parent": {
        "__id__": 7
      },
      "_components": [
        {
          "__type__": "cc.Sprite",
          "node": {
            "__id__": 11
          },
          "_spriteFrame": {
            "__uuid__": "d3X5g1985D6KoxbmYeyMNA"
          },
          "_sizeMode": 0
        },
        {
          "__type__": "cc.Button",
          "node": {
            "__id__": 11
          },
          "transition": 3,
          "clickEvents": [
            {
              "__type__": "cc.ClickEvent",
              "target": {
                "__id__": 3
              },
              "component": "About",
              "handler": "sendEmail"
            }
          ],
          "_N$target": {
            "__id__": 11
          }
        }
      ],
      "_contentSize": {
        "__type__": "cc.Size",
        "width": 50,
        "height": 50
      },
      "_position": {
        "__type__": "cc.Vec2",
        "x": 105
      }
    },
    {
      "__type__": "cc.Node",
      "_parent": {
        "__id__": 2
      },
      "_prefab": {
        "__type__": "cc.PrefabInfo",
        "root": {
          "__id__": 12
        },
        "asset": {
          "__uuid__": "ddW+Rq1vhINYN5rEfARmem"
        },
        "fileId": "f94e8AmRZD5b6uhTO8zV8h",
        "sync": true
      },
      "_name": "Back",
      "_position": {
        "__type__": "cc.Vec2",
        "x": -425,
        "y": 215
      }
    }
  ],
  {
    "__type__": "cc.SpriteFrame",
    "content": {
      "name": "logo-alpha",
      "texture": "97c8v0fphEJaqhkN91zz3U",
      "rect": [
        0,
        26,
        250,
        224
      ],
      "offset": [
        0,
        -13
      ],
      "originalSize": [
        250,
        250
      ]
    }
  },
  {
    "__type__": "cc.SpriteFrame",
    "content": {
      "name": "web",
      "texture": "1d139866a",
      "rect": [
        626,
        3,
        188,
        188
      ],
      "offset": [
        0,
        0
      ],
      "originalSize": [
        200,
        200
      ]
    }
  },
  {
    "__type__": "cc.SpriteFrame",
    "content": {
      "name": "email",
      "texture": "1d139866a",
      "rect": [
        214,
        3,
        200,
        200
      ],
      "offset": [
        0,
        0
      ],
      "originalSize": [
        200,
        200
      ]
    }
  }
]